{
  "trial_id": 6,
  "config": {
    "input_size": 3883,
    "output_size": 214,
    "hidden_sizes": [
      2048,
      1024,
      1024,
      512
    ],
    "lr": 0.0001994204033051701,
    "weight_decay": 5.285382203816731e-06,
    "batch_size": 128,
    "max_epochs": 500,
    "dropout_rate": 0.30499832889131046,
    "activation": "selu",
    "optimizer": "sgd_momentum",
    "learning_rate_schedule": "cosine",
    "batch_norm": "false"
  },
  "error": 0.010446783698474368,
  "additional_info": {
    "training_time": 783.0240778923035,
    "epochs": 500,
    "final_train_loss": null
  },
  "job_id": "43259579",
  "submit_time": "2025-04-29T13:52:36.680592",
  "complete_time": "2025-04-29T14:06:41.948245"
}